<?xml version="1.0" encoding="utf-8"?><soap:Envelope xmlns:soap="http://schemas.xmlsoap.org/soap/envelope/" xmlns:xsi="http://www.w3.org/2001/XMLSchema-instance" xmlns:xsd="http://www.w3.org/2001/XMLSchema"><soap:Header><FEHeaderInfo xmlns="http://ar.gov.afip.dif.FEV1/"><ambiente>Produccion - se6</ambiente><fecha>2023-12-23T20:00:21.1983022-03:00</fecha><id>5.4.0.0</id></FEHeaderInfo></soap:Header><soap:Body><FECAESolicitarResponse xmlns="http://ar.gov.afip.dif.FEV1/"><FECAESolicitarResult><FeCabResp><Cuit>20085031202</Cuit><PtoVta>5</PtoVta><CbteTipo>6</CbteTipo><FchProceso>20231223200021</FchProceso><CantReg>1</CantReg><Resultado>A</Resultado><Reproceso>N</Reproceso></FeCabResp><FeDetResp><FECAEDetResponse><Concepto>1</Concepto><DocTipo>94</DocTipo><DocNro>188884083</DocNro><CbteDesde>1548</CbteDesde><CbteHasta>1548</CbteHasta><CbteFch>20231221</CbteFch><Resultado>A</Resultado><CAE>73512658715247</CAE><CAEFchVto>20231231</CAEFchVto></FECAEDetResponse></FeDetResp></FECAESolicitarResult></FECAESolicitarResponse></soap:Body></soap:Envelope>
