<?xml version="1.0" encoding="utf-8"?><soap:Envelope xmlns:soap="http://schemas.xmlsoap.org/soap/envelope/" xmlns:xsi="http://www.w3.org/2001/XMLSchema-instance" xmlns:xsd="http://www.w3.org/2001/XMLSchema"><soap:Header><FEHeaderInfo xmlns="http://ar.gov.afip.dif.FEV1/"><ambiente>HomologacionExterno - efa</ambiente><fecha>2023-01-10T16:34:54.88454-03:00</fecha><id>5.1.0.0</id></FEHeaderInfo></soap:Header><soap:Body><FECAESolicitarResponse xmlns="http://ar.gov.afip.dif.FEV1/"><FECAESolicitarResult><FeCabResp><Cuit>20085031202</Cuit><PtoVta>1</PtoVta><CbteTipo>6</CbteTipo><FchProceso>20230110163454</FchProceso><CantReg>1</CantReg><Resultado>A</Resultado><Reproceso>N</Reproceso></FeCabResp><FeDetResp><FECAEDetResponse><Concepto>1</Concepto><DocTipo>94</DocTipo><DocNro>1342407725</DocNro><CbteDesde>2</CbteDesde><CbteHasta>2</CbteHasta><CbteFch>20230110</CbteFch><Resultado>A</Resultado><CAE>73022074706818</CAE><CAEFchVto>20230120</CAEFchVto></FECAEDetResponse></FeDetResp></FECAESolicitarResult></FECAESolicitarResponse></soap:Body></soap:Envelope>
