<?xml version="1.0" encoding="utf-8"?><soap:Envelope xmlns:soap="http://schemas.xmlsoap.org/soap/envelope/" xmlns:xsi="http://www.w3.org/2001/XMLSchema-instance" xmlns:xsd="http://www.w3.org/2001/XMLSchema"><soap:Header><FEHeaderInfo xmlns="http://ar.gov.afip.dif.FEV1/"><ambiente>Produccion - Se8</ambiente><fecha>2023-07-21T02:08:31.4892087-03:00</fecha><id>5.2.1.0</id></FEHeaderInfo></soap:Header><soap:Body><FECAESolicitarResponse xmlns="http://ar.gov.afip.dif.FEV1/"><FECAESolicitarResult><FeCabResp><Cuit>20085031202</Cuit><PtoVta>5</PtoVta><CbteTipo>6</CbteTipo><FchProceso>20230721020831</FchProceso><CantReg>1</CantReg><Resultado>A</Resultado><Reproceso>N</Reproceso></FeCabResp><FeDetResp><FECAEDetResponse><Concepto>1</Concepto><DocTipo>94</DocTipo><DocNro>11111</DocNro><CbteDesde>504</CbteDesde><CbteHasta>504</CbteHasta><CbteFch>20230721</CbteFch><Resultado>A</Resultado><CAE>73292207587530</CAE><CAEFchVto>20230731</CAEFchVto></FECAEDetResponse></FeDetResp></FECAESolicitarResult></FECAESolicitarResponse></soap:Body></soap:Envelope>
